{
"do_train": true,
"do_eval": true,
"do_test": true,
"save_steps": 1000,
"model_name_or_path": "t5-base",
"tokenizer_name": "t5-base",
"save_total_limit": 1,
"load_best_model_at_end": true,
"metric_for_best_model": "average_metrics",
"greater_is_better": true,
"evaluation_strategy": "epoch",
"split_validation_test": true,
"dataset_config_name": ["en"],
"eval_dataset_config_name": ["en"],
"test_dataset_config_name": ["en"],
"predict_with_generate": true,
"adapter_config_name": "adapter",
"train_task_adapters": true,

"logging_dir": "outputs/debug_1/trainer_logs",
"output_dir": "outputs/debug_1",
"compute_time": true,
"compute_memory": true,
"print_num_parameters": true,

"add_layer_norm_before_adapter": false, 
"add_layer_norm_after_adapter": false,
"unfreeze_lm_head": false,
"unfreeze_layer_norms": true,
"overwrite_output_dir": true,

"project_name": "tt_debug",
"experiment_name": "debug_1",
"task_name": "mrpc",
"eval_dataset_name": "mrpc", 
"test_dataset_name": "mrpc",
"num_train_epochs": 1,
"logging_steps":5,
"learning_rate": 3e-4,
"warmup_steps": 500,
"per_device_train_batch_size": 25,
"per_device_eval_batch_size": 50,
"max_source_length": 128,
"non_linearity": "gelu_new",
"task_reduction_factor": 32,
"task_expansion_factor": 0,
"tensor_train_adapters": true,
"tt_rank": 1,
"tt_d": 5,
"reverse_out_shape": false,
"factorize_smaller_dim": true,
"tensor_train_single": false,
"use_ScaleNorm": false,
"ScaleNorm_scale": 1.0,
"use_TTLayerNorm": true,
"use_TTBias": true,
}
